MANIFEST.in
setup.py
lan_echarts/__init__.py
lan_echarts/lan_echarts.py
lan_echarts.egg-info/PKG-INFO
lan_echarts.egg-info/SOURCES.txt
lan_echarts.egg-info/dependency_links.txt
lan_echarts.egg-info/requires.txt
lan_echarts.egg-info/top_level.txt
lan_echarts/static/echarts.common.js
lan_echarts/static/echarts.common.min.js
lan_echarts/static/echarts.esm.js
lan_echarts/static/echarts.esm.min.js
lan_echarts/static/echarts.html
lan_echarts/static/echarts.js
lan_echarts/static/echarts.min.js
lan_echarts/static/echarts.simple.js
lan_echarts/static/echarts.simple.min.js
lan_echarts/static/jquery-3.6.0.min.js
lan_echarts/static/extension/bmap.js
lan_echarts/static/extension/bmap.js.map
lan_echarts/static/extension/bmap.min.js
lan_echarts/static/extension/dataTool.js
lan_echarts/static/extension/dataTool.js.map
lan_echarts/static/extension/dataTool.min.js