Metadata-Version: 2.1
Name: lan-echarts
Version: 0.0.4
Summary: python echarts
Home-page: https://github.com/
Author: lan_echarts
Author-email: shiwolang@live.com
License: MIT Licence
Keywords: pip,echarts
Platform: any
